.gitignore
README.rst
buildout.cfg
setup.cfg
setup.py
buildoutpip/__init__.py
buildoutpip.egg-info/PKG-INFO
buildoutpip.egg-info/SOURCES.txt
buildoutpip.egg-info/dependency_links.txt
buildoutpip.egg-info/entry_points.txt
buildoutpip.egg-info/not-zip-safe
buildoutpip.egg-info/paster_plugins.txt
buildoutpip.egg-info/top_level.txt