Metadata-Version: 1.0
Name: buildoutpip
Version: 0.1dev
Summary: Buildout extension to install from pip requirements files
Home-page: http://github.com/taras/buildoutpip
Author: Taras Mankovski
Author-email: tarasm@gmail.com
License: BSD License
Keywords: buildout extension pip
Platform: UNKNOWN
